MANIFEST.in
README
health_history_report.xml
setup.py
./__init__.py
./health_history_report.xml
./tryton.cfg
./locale/ar.po
./locale/de.po
./locale/el.po
./locale/es.po
./locale/fr.po
./locale/it_IT.po
./locale/ja_JP.po
./locale/lo.po
./locale/pt_BR.po
./locale/zh_CN.po
./report/__init__.py
./report/patient_evaluation.odt
./report/patient_evaluation_report.py
./tests/__init__.py
./tests/test_health_history.py
locale/ar.po
locale/de.po
locale/el.po
locale/es.po
locale/fr.po
locale/it_IT.po
locale/ja_JP.po
locale/lo.po
locale/pt_BR.po
locale/zh_CN.po
report/patient_evaluation.odt
trytond_health_history.egg-info/PKG-INFO
trytond_health_history.egg-info/SOURCES.txt
trytond_health_history.egg-info/dependency_links.txt
trytond_health_history.egg-info/entry_points.txt
trytond_health_history.egg-info/not-zip-safe
trytond_health_history.egg-info/requires.txt
trytond_health_history.egg-info/top_level.txt